csvexporter.py
modules/.DS_Store
modules/RowCreator.py
modules/__init__.py
modules/csvExporter.py
modules/safetypy.py
iauditor_reporting_tool-0.1.1.dist-info/entry_points.txt
iauditor_reporting_tool-0.1.1.dist-info/WHEEL
iauditor_reporting_tool-0.1.1.dist-info/METADATA
iauditor_reporting_tool-0.1.1.dist-info/RECORD
